LICENSE
MANIFEST.in
README.rst
setup.py
bin/otp
otp/__init__.py
otp/_version.py
otp/core.py
otp/otp.py
otp/progress.py
otp/qr_code.py
otp/token.py
otp_py.egg-info/PKG-INFO
otp_py.egg-info/SOURCES.txt
otp_py.egg-info/dependency_links.txt
otp_py.egg-info/requires.txt
otp_py.egg-info/top_level.txt