Metadata-Version: 1.2
Name: otp-py
Version: 0.5
Summary: Generate one time passwords
Home-page: http://github.com/karakays/otp-py/
Author: Selçuk Karakayalı
Author-email: skarakayali@gmail.com
Maintainer: Selçuk Karakayalı
License: MIT
Keywords: otp,otp-codes,otp-generator,authenticator
Platform: UNKNOWN
Classifier: Programming Language :: Python :: 3.6
Classifier: Programming Language :: Python :: 3.7
Classifier: Programming Language :: Python :: 3.8
Classifier: License :: OSI Approved :: MIT License
Requires-Python: >=3.6
